README.md
setup.py
dbapix/__init__.py
dbapix/connection.py
dbapix/cursor.py
dbapix/engine.py
dbapix/params.py
dbapix/query.py
dbapix/registry.py
dbapix/row.py
dbapix.egg-info/PKG-INFO
dbapix.egg-info/SOURCES.txt
dbapix.egg-info/dependency_links.txt
dbapix.egg-info/requires.txt
dbapix.egg-info/top_level.txt
dbapix/drivers/__init__.py
dbapix/drivers/mysqldb.py
dbapix/drivers/pymysql.py
dbapix/drivers/sqlite3.py
dbapix/drivers/psycopg2/__init__.py