Metadata-Version: 1.1
Name: dbapix
Version: 2.0.0
Summary: A unification of, and extension to, several DB-API 2.0 drivers.
Home-page: http://github.com/mikeboers/dbapix
Author: Mike Boers
Author-email: dbapix@mikeboers.com
License: BSD-3
Platform: UNKNOWN
Classifier: Intended Audience :: Developers
Classifier: License :: OSI Approved :: BSD License
Classifier: Natural Language :: English
Classifier: Operating System :: OS Independent
Classifier: Programming Language :: Python :: 2
Classifier: Programming Language :: Python :: 3
Classifier: Topic :: Software Development :: Libraries :: Python Modules
